ica/__init__.py
ica/__main__.py
ica/analyzers/__init__.py
ica/analyzers/attachment_totals.py
ica/analyzers/count_phrases.py
ica/analyzers/from_sql.py
ica/analyzers/message_totals.py
ica/analyzers/most_frequent_emojis.py
ica/analyzers/totals_by_day.py
ica/analyzers/transcript.py
ica/cli.py
ica/contact.py
ica/core.py
ica/exceptions.py
ica/py.typed
ica/queries/attachments.sql
ica/queries/contact.sql
ica/queries/messages.sql
imessage_conversation_analyzer-3.1.0.dist-info/WHEEL
imessage_conversation_analyzer-3.1.0.dist-info/entry_points.txt
imessage_conversation_analyzer-3.1.0.dist-info/METADATA
imessage_conversation_analyzer-3.1.0.dist-info/RECORD
