Metadata-Version: 2.4
Name: imessage-conversation-analyzer
Version: 3.1.0
Summary: Analyzes the entire history of a macOS Messages conversation
Keywords: apple,imessage,messages,macos,conversation,chat,analysis,pandas
Author: Caleb Evans
Author-email: Caleb Evans <caleb@calebevans.me>
License-Expression: MIT
Requires-Dist: pandas
Requires-Dist: pyarrow
Requires-Dist: tabulate
Requires-Dist: openpyxl
Requires-Dist: pytypedstream
Requires-Dist: phonenumbers
Requires-Dist: tzlocal
Requires-Dist: emoji
Requires-Dist: duckdb
Maintainer: Caleb Evans
Maintainer-email: Caleb Evans <caleb@calebevans.me>
Requires-Python: >=3.9
Project-URL: homepage, https://github.com/caleb531/imessage-conversation-analyzer
Project-URL: documentation, https://github.com/caleb531/imessage-conversation-analyzer#readme
Project-URL: repository, https://github.com/caleb531/imessage-conversation-analyzer
Project-URL: changelog, https://github.com/caleb531/imessage-conversation-analyzer/releases
